SPEARS/SPEARS.py
SPEARS/__init__.py
SPEARS/data/emission_lines.json
spears-2.0.5.dist-info/METADATA
spears-2.0.5.dist-info/WHEEL
spears-2.0.5.dist-info/top_level.txt
spears-2.0.5.dist-info/RECORD
