Metadata-Version: 2.4
Name: SPEARS
Version: 2.0.5
Home-page: https://pypi.org/project/SPEARS/
Author: Justin Domagala-Tang
License: MIT
Classifier: License :: OSI Approved :: MIT License
Classifier: Programming Language :: Python :: 3
Requires-Python: >=3.7
Requires-Dist: requests
Requires-Dist: sparclclient
Requires-Dist: specutils>=1.0
Requires-Dist: astropy>=5.0
Requires-Dist: scipy>=1.7
Requires-Dist: numpy>=1.21
Requires-Dist: alive-progress
Requires-Dist: matplotlib>=3.0
Dynamic: author
Dynamic: classifier
Dynamic: description
Dynamic: description-content-type
Dynamic: home-page
Dynamic: license
Dynamic: requires-dist
Dynamic: requires-python
